{
    "images": [
        {
            "file_name": "sample1.jpg",
            "height": 3888,
            "width": 5184,
            "id": 1
        },
        {
            "file_name": "sample2.jpg",
            "height": 1871,
            "width": 2878,
            "id": 2
        }
    ],
    "categories": [
        {
            "skeleton": [],
            "keypoints": [],
            "keypoint_colors": [],
            "color": "#A8D695",
            "supercategory": "animal",
            "id": 1,
            "name": "animal"
        }
    ],
    "annotations": [
        {
            "num_keypoints": 0,
            "keypoints": [],
            "segmentation": [
                [
                    1404.68,
                    979.66,
                    2678.88,
                    979.66,
                    2678.88,
                    3012.59,
                    1404.68,
                    3012.59,
                    1404.68,
                    979.66
                ]
            ],
            "iscrowd": 0,
            "area": 2590359.4060000004,
            "image_id": 1,
            "bbox": [
                1404.68,
                979.66,
                1274.2,
                2032.9300000000003
            ],
            "rotation": 0,
            "category_id": 1,
            "id": 1,
            "attributes": {}
        },
        {
            "num_keypoints": 0,
            "keypoints": [],
            "segmentation": [
                [
                    2696.25,
                    834.87,
                    3906.74,
                    834.87,
                    3906.74,
                    3105.26,
                    2696.25,
                    3105.26,
                    2696.25,
                    834.87
                ]
            ],
            "iscrowd": 0,
            "area": 2748284.3911,
            "image_id": 1,
            "bbox": [
                2696.25,
                834.87,
                1210.4899999999998,
                2270.3900000000003
            ],
            "rotation": 0,
            "category_id": 1,
            "id": 2,
            "attributes": {}
        },
        {
            "num_keypoints": 0,
            "keypoints": [],
            "segmentation": [
                [
                    1360.99,
                    170.75,
                    2779.05,
                    170.75,
                    2779.05,
                    1775.47,
                    1360.99,
                    1775.47,
                    1360.99,
                    170.75
                ]
            ],
            "iscrowd": 0,
            "area": 2275589.2432000004,
            "image_id": 2,
            "bbox": [
                1360.99,
                170.75,
                1418.0600000000002,
                1604.72
            ],
            "rotation": 0,
            "category_id": 1,
            "id": 3,
            "attributes": {}
        }
    ]
}